muscledagents/__init__.py
muscledagents/__version__.py
muscledagents/envs/__init__.py
muscledagents/envs/mujoco/__init__.py
muscledagents/envs/mujoco/base_muscled_env.py
muscledagents/envs/mujoco/mujoco_env.py
muscledagents/envs/mujoco/muscled_ant.py
muscledagents/envs/mujoco/muscled_hopper.py
muscledagents/envs/mujoco/muscled_reacher.py
muscledagents-0.0.2.dist-info/METADATA
muscledagents-0.0.2.dist-info/RECORD
muscledagents-0.0.2.dist-info/WHEEL
muscledagents-0.0.2.dist-info/top_level.txt
