Metadata-Version: 2.1
Name: muscledagents
Version: 0.0.2
Summary: Muscle rigged models and environments for machine learning experiments.
Home-page: https://github.com/iandanforth/muscledagents
Author: Ian Danforth
Author-email: iandanforth@gmail.com
License: MIT + No Military Use
Platform: UNKNOWN
Classifier: Programming Language :: Python
Classifier: Programming Language :: Python :: 3
Classifier: Programming Language :: Python :: 3.6
Classifier: Programming Language :: Python :: Implementation :: CPython
Classifier: Programming Language :: Python :: Implementation :: PyPy
Requires-Python: >=3.6.0
Requires-Dist: gym
Requires-Dist: pymuscle
Requires-Dist: mujoco-py (<1.50.2,>=1.50.1)
